README.rst
setup.cfg
setup.py
fluxi/__init__.py
fluxi.egg-info/PKG-INFO
fluxi.egg-info/SOURCES.txt
fluxi.egg-info/dependency_links.txt
fluxi.egg-info/top_level.txt