Metadata-Version: 1.1
Name: fluxi
Version: 0.0.1.dev0
Summary: Fluxi
Home-page: https://www.koehlma.de/fluxi
Author: Maximilian Köhl
Author-email: mail@koehlma.de
License: UNKNOWN
Platform: UNKNOWN
Classifier: Development Status :: 1 - Planning
Classifier: Intended Audience :: Developers
Classifier: Operating System :: OS Independent
Classifier: Programming Language :: Python :: 3
